gspot_django_auth/__init__.py
gspot_django_auth/authentication.py
gspot_django_auth/exceptions.py
gspot_django_auth/factory.py
gspot_django_auth/models.py
gspot_django_auth/permissions.py
gspot_django_auth/redis_client.py
gspot_django_auth/test_auth.py
gspot_django_auth/token.py
gspot_django_auth/management/__init__.py
gspot_django_auth/management/commands/__init__.py
gspot_django_auth/management/commands/load_test_tokens.py
gspot_django_auth/permissions/__init__.py
gspot_django_auth/permissions/permissons.py
gspot_django_auth/permissions/validators.py
gspot_django_auth/permissions/verifiers.py
gspot_django_auth-0.1.5.dist-info/LICENSE
gspot_django_auth-0.1.5.dist-info/METADATA
gspot_django_auth-0.1.5.dist-info/WHEEL
gspot_django_auth-0.1.5.dist-info/top_level.txt
gspot_django_auth-0.1.5.dist-info/RECORD
