Metadata-Version: 2.1
Name: gspot-django-auth
Version: 0.1.5
Summary: A Django app for auth.
Home-page: https://github.com/DJWOMS/GSpot
Author: Kosenko Viktor
Author-email: oxpaoff <kosenkoviktor11@gmail.com>
License: MIT License
Project-URL: Homepage, https://github.com/oxpaoff/gspot_auth
Project-URL: Bug Tracker, https://github.com/oxpaoff/gspot_auth/issues
Classifier: Programming Language :: Python :: 3
Classifier: License :: OSI Approved :: MIT License
Classifier: Operating System :: OS Independent
Requires-Python: >=3.10
License-File: LICENSE
Requires-Dist: asgiref (==3.7.2)
Requires-Dist: async-timeout (==4.0.2)
Requires-Dist: Django (==4.2.2)
Requires-Dist: djangorestframework (==3.14.0)
Requires-Dist: PyJWT (==2.7.0)
Requires-Dist: pytz (==2023.3)
Requires-Dist: redis (==4.6.0)
Requires-Dist: sqlparse (==0.4.4)
Requires-Dist: typing-extensions (==4.6.3)
